aphyt/__init__.py
aphyt/cip/__init__.py
aphyt/cip/cip.py
aphyt/cip/cip_attributes.py
aphyt/cip/cip_datatypes.py
aphyt/cip/cip_services.py
aphyt/eip/__init__.py
aphyt/eip/eip.py
aphyt/eip/cip_objects/__init__.py
aphyt/eip/cip_objects/tcp_interface.py
aphyt/omron/__init__.py
aphyt/omron/f4_series.py
aphyt/omron/k6pm_th.py
aphyt/omron/n_series.py
aphyt/omron/omron_datatypes.py
aphyt/omron/v4_series.py
aphyt/tkmi/Transparent_Pixel.png
aphyt/tkmi/__init__.py
aphyt/tkmi/helper.py
aphyt/tkmi/tkmi_main.py
aphyt/tkmi/widgets.py
aphyt-0.1.24.dist-info/licenses/LICENSE.txt
aphyt-0.1.24.dist-info/METADATA
aphyt-0.1.24.dist-info/WHEEL
aphyt-0.1.24.dist-info/top_level.txt
aphyt-0.1.24.dist-info/RECORD
