Metadata-Version: 2.4
Name: aphyt
Version: 0.1.24
Summary: A library to communicate with Omron NX and NJ PLC and motion controllers
Home-page: https://github.com/aphyt/aphytcomm
Author: Joseph Ryan
Author-email: jr@aphyt.com
Classifier: Programming Language :: Python :: 3
Classifier: License :: OSI Approved :: GNU General Public License v2 (GPLv2)
Classifier: Operating System :: OS Independent
Requires-Python: >=3.8
License-File: LICENSE.txt
Dynamic: author
Dynamic: author-email
Dynamic: classifier
Dynamic: description
Dynamic: description-content-type
Dynamic: home-page
Dynamic: license-file
Dynamic: requires-python
Dynamic: summary
